odoo8_addon_account_banking_sepa_direct_debit-8.0.0.5.1.99.dev4-py3.8-nspkg.pth
odoo_addons/account_banking_sepa_direct_debit/README.rst
odoo_addons/account_banking_sepa_direct_debit/__init__.py
odoo_addons/account_banking_sepa_direct_debit/__openerp__.py
odoo_addons/account_banking_sepa_direct_debit/data/mandate_expire_cron.xml
odoo_addons/account_banking_sepa_direct_debit/data/pain.008.001.02.xsd
odoo_addons/account_banking_sepa_direct_debit/data/pain.008.001.03.xsd
odoo_addons/account_banking_sepa_direct_debit/data/pain.008.001.04.xsd
odoo_addons/account_banking_sepa_direct_debit/data/payment_type_sdd.xml
odoo_addons/account_banking_sepa_direct_debit/data/report_paperformat.xml
odoo_addons/account_banking_sepa_direct_debit/demo/sepa_direct_debit_demo.xml
odoo_addons/account_banking_sepa_direct_debit/i18n/account_banking_sepa_direct_debit.pot
odoo_addons/account_banking_sepa_direct_debit/i18n/am.po
odoo_addons/account_banking_sepa_direct_debit/i18n/ar.po
odoo_addons/account_banking_sepa_direct_debit/i18n/bg.po
odoo_addons/account_banking_sepa_direct_debit/i18n/bs.po
odoo_addons/account_banking_sepa_direct_debit/i18n/ca.po
odoo_addons/account_banking_sepa_direct_debit/i18n/ca_ES.po
odoo_addons/account_banking_sepa_direct_debit/i18n/cs.po
odoo_addons/account_banking_sepa_direct_debit/i18n/da.po
odoo_addons/account_banking_sepa_direct_debit/i18n/de.po
odoo_addons/account_banking_sepa_direct_debit/i18n/el_GR.po
odoo_addons/account_banking_sepa_direct_debit/i18n/en_AU.po
odoo_addons/account_banking_sepa_direct_debit/i18n/en_GB.po
odoo_addons/account_banking_sepa_direct_debit/i18n/es.po
odoo_addons/account_banking_sepa_direct_debit/i18n/es_AR.po
odoo_addons/account_banking_sepa_direct_debit/i18n/es_CL.po
odoo_addons/account_banking_sepa_direct_debit/i18n/es_CO.po
odoo_addons/account_banking_sepa_direct_debit/i18n/es_CR.po
odoo_addons/account_banking_sepa_direct_debit/i18n/es_DO.po
odoo_addons/account_banking_sepa_direct_debit/i18n/es_EC.po
odoo8_addon_account_banking_sepa_direct_debit-8.0.0.5.1.99.dev4.dist-info/METADATA
odoo8_addon_account_banking_sepa_direct_debit-8.0.0.5.1.99.dev4.dist-info/WHEEL
odoo8_addon_account_banking_sepa_direct_debit-8.0.0.5.1.99.dev4.dist-info/namespace_packages.txt
odoo8_addon_account_banking_sepa_direct_debit-8.0.0.5.1.99.dev4.dist-info/top_level.txt
odoo8_addon_account_banking_sepa_direct_debit-8.0.0.5.1.99.dev4.dist-info/RECORD
